discourses/__init__.py
discourses/client.py
discourses/constants.py
discourses/exceptions.py
discourses/models.py
discourses/py.typed
discourses-1.1.4.dist-info/licenses/LICENSE
discourses-1.1.4.dist-info/METADATA
discourses-1.1.4.dist-info/WHEEL
discourses-1.1.4.dist-info/top_level.txt
discourses-1.1.4.dist-info/RECORD
