Metadata-Version: 2.4
Name: discourses
Version: 1.1.4
Summary: Official Python SDK for Discourses — Era-calibrated financial sentiment analysis
Author-email: "discourses.io" <support@discourses.io>
License: MIT
Project-URL: Homepage, https://discourses.io
Project-URL: Documentation, https://discourses.io/documentation
Project-URL: Repository, https://github.com/romanmichaelpaolucci/discourses
Project-URL: Issues, https://github.com/romanmichaelpaolucci/discourses/issues
Project-URL: Changelog, https://github.com/romanmichaelpaolucci/discourses/releases
Keywords: discourses,sentiment,sentiment-analysis,finance,fintech,nlp,trading,market-analysis,api,sdk
Classifier: Development Status :: 5 - Production/Stable
Classifier: Intended Audience :: Developers
Classifier: Intended Audience :: Financial and Insurance Industry
Classifier: Intended Audience :: Science/Research
Classifier: License :: OSI Approved :: MIT License
Classifier: Operating System :: OS Independent
Classifier: Programming Language :: Python :: 3
Classifier: Programming Language :: Python :: 3.8
Classifier: Programming Language :: Python :: 3.9
Classifier: Programming Language :: Python :: 3.10
Classifier: Programming Language :: Python :: 3.11
Classifier: Programming Language :: Python :: 3.12
Classifier: Topic :: Office/Business :: Financial
Classifier: Topic :: Scientific/Engineering :: Artificial Intelligence
Classifier: Typing :: Typed
Requires-Python: >=3.8
License-File: LICENSE
Requires-Dist: requests>=2.25.0
Provides-Extra: dev
Requires-Dist: black>=23.0.0; extra == "dev"
Requires-Dist: mypy>=1.0.0; extra == "dev"
Requires-Dist: types-requests>=2.25.0; extra == "dev"
Dynamic: license-file
